httpie_apikey_auth.py
httpie_apikey_auth-0.1.1.dist-info/LICENSE
httpie_apikey_auth-0.1.1.dist-info/METADATA
httpie_apikey_auth-0.1.1.dist-info/WHEEL
httpie_apikey_auth-0.1.1.dist-info/entry_points.txt
httpie_apikey_auth-0.1.1.dist-info/top_level.txt
httpie_apikey_auth-0.1.1.dist-info/RECORD
