Metadata-Version: 2.1
Name: httpie-apikey-auth
Version: 0.1.1
Summary: Elastic ApiKey plugin for HTTPie.
Home-page: https://github.com/dcode/httpie-apikey-auth
Author: Derek Ditch
Author-email: dcode@rocknsm.io
License: MIT
Download-URL: https://github.com/dcode/httpie-apikey-auth
Platform: UNKNOWN
Classifier: Development Status :: 4 - Beta
Classifier: Programming Language :: Python
Classifier: Intended Audience :: Developers
Classifier: Environment :: Plugins
Classifier: License :: OSI Approved :: MIT License
Classifier: Topic :: Internet :: WWW/HTTP
Classifier: Topic :: Utilities
Requires-Dist: httpie (>=0.7.0)
